hearthsim/instrumentation/__init__.py
hearthsim/instrumentation/django_influxdb.py
hearthsim/instrumentation/ssm.py
hearthsim_instrumentation-0.1.0.dist-info/DESCRIPTION.rst
hearthsim_instrumentation-0.1.0.dist-info/METADATA
hearthsim_instrumentation-0.1.0.dist-info/RECORD
hearthsim_instrumentation-0.1.0.dist-info/WHEEL
hearthsim_instrumentation-0.1.0.dist-info/metadata.json
hearthsim_instrumentation-0.1.0.dist-info/top_level.txt
hearthsim_instrumentation-0.1.0.dist-info/zip-safe
