Metadata-Version: 2.0
Name: hearthsim-instrumentation
Version: 0.1.0
Summary: HearthSim instrumentation common library
Home-page: https://github.com/HearthSim/hearthsim-instrumentation/
Author: Jerome Leclanche
Author-email: jerome@leclan.ch
License: UNKNOWN
Download-URL: https://github.com/HearthSim/hearthsim-instrumentation/tarball/master
Platform: UNKNOWN
Classifier: Development Status :: 3 - Alpha
Classifier: Intended Audience :: Developers
Classifier: License :: OSI Approved :: MIT License
Classifier: Programming Language :: Python
Classifier: Programming Language :: Python :: 3
Classifier: Programming Language :: Python :: 3.6
Classifier: Topic :: Games/Entertainment
Classifier: Topic :: Internet :: WWW/HTTP
Requires-Dist: boto3
Requires-Dist: influxdb
